[
  {
    "market": "CC Fresh",
    "source": "ccfresh",
    "title": "🛍️⭐️CCFresh Weekend Member Sale!⭐️💙 Join us this weekend, JUNE 20 - 21, for our exclusive Member Sale at 📍Locations:...",
    "link": "https://m.facebook.com/ccfreshwholesale/posts/pfbid05DmD5seFZSCSuGk8AedtXtVpbVjJJAEXUMUCVqfnnBHxaMe89p3ceMNTRirgAQ6hl",
    "image": "https://scontent-den2-1.xx.fbcdn.net/v/t39.30808-6/725249886_1440163781486168_6646069490080833967_n.jpg?stp=dst-jpg_p526x296_tt6&_nc_cat=109&ccb=1-7&_nc_sid=e5c1b6&_nc_ohc=xi3ucMcjvuoQ7kNvwHG7Kad&_nc_oc=AdqmYpdmNkk-HnDkXq88r1DfuRoxOqr1MIBkFWNMQcFWThHjaqpqyZ5BYBRNOPkGxac&_nc_zt=23&_nc_ht=scontent-den2-1.xx&_nc_gid=wzdspb1jZ1UpIkdGZ5zlxA&_nc_ss=7b289&oh=00_Af-wgyq1TNqLrcw1ZPbZLfNOE1dRcbsLNJSpHt8p_niF7g&oe=6A3F79B7",
    "date": "Fri, 19 Jun 2026 09:15:27 GMT"
  },
  {
    "market": "CC Fresh",
    "source": "ccfresh",
    "title": "Nak berjimat bila beli banyak? 📦🔥 CCFresh Miri kini ada promosi carton sale untuk pelbagai produk terpilih 😍 Lagi ban...",
    "link": "https://www.facebook.com/reel/1286197116920657/",
    "image": "https://scontent-ams2-1.xx.fbcdn.net/v/t15.5256-10/722909403_1365428613124620_5071502100021622888_n.jpg?stp=dst-jpg_p565x565_tt6&_nc_cat=106&ccb=1-7&_nc_sid=1a6f08&_nc_ohc=nnfB6i4f-xoQ7kNvwGkRH_F&_nc_oc=AdrvcSMTw4jMEncICHBgyLKugJr-g01qvBR6dKGC0QqmfgwPrJh022C6hmbdLocv5MvuF7Kh17EcAktWjiSiiQ6H&_nc_zt=23&_nc_ht=scontent-ams2-1.xx&_nc_gid=RnQcY5ZxZmtOaHhW6f_jzw&_nc_ss=7b289&oh=00_Af8sh1CKNkjbZBq4h13wtANGz84_7qsNlWSrZSfkamqDAw&oe=6A3EED83",
    "date": "Wed, 17 Jun 2026 10:46:17 GMT"
  },
  {
    "market": "CC Fresh",
    "source": "ccfresh",
    "title": "🛍 🛒 Program Jualan RAHMAH MADANI akan diadakan seperti ketetapan di bawah: 🏬Tempat: CC Fresh Wholesale & Supermarket...",
    "link": "https://m.facebook.com/ccfreshwholesale/posts/pfbid02CiJso4qL7KQWNPpQN9YrEJvu5gdDcPreyC8djaGb3juKimpMLBSdQeGCJqwTZtY7l",
    "image": "https://scontent-sea5-1.xx.fbcdn.net/v/t39.30808-6/724164254_1443594307796659_587205479549932803_n.jpg?stp=dst-jpg_p526x296_tt6&_nc_cat=110&ccb=1-7&_nc_sid=e21142&_nc_ohc=X8fdSV4hiH0Q7kNvwGDU0YH&_nc_oc=AdpjXEyieguaGIpTyRgyRWuBgXE7NBz-0SFgRNaw2dXsrifmRyNf2IZvEG8DkiPNOJ4&_nc_zt=23&_nc_ht=scontent-sea5-1.xx&_nc_gid=RlXgHoU11GS2CynmDL0FWA&_nc_ss=7b289&oh=00_Af_OEzMGcc0JROcs5WnsUbJlCwuzp8w9Zuiende00NrD9A&oe=6A3ACBEB",
    "date": "Tue, 16 Jun 2026 09:01:32 GMT"
  },
  {
    "market": "CC Fresh",
    "source": "ccfresh",
    "title": "Shopping di CCFresh Miri rasa macam orang kaya 😎🔥 Harga jimat tapi troli penuh puas hati 😍 Banyak promo untuk carton...",
    "link": "https://www.facebook.com/reel/1685299655947142/",
    "image": "https://scontent-cdg4-1.xx.fbcdn.net/v/t15.5256-10/720398291_1006483221961566_5859529262490978872_n.jpg?stp=dst-jpg_p565x565_tt6&_nc_cat=104&ccb=1-7&_nc_sid=1a6f08&_nc_ohc=1lZZYj5sEkYQ7kNvwEtFfa5&_nc_oc=AdpH1Zs6I0smdHveeCfOZJrJTptIL4MRFanM-I2krc6aT5LSzDElnyk7Gnt1Hf1e2o8&_nc_zt=23&_nc_ht=scontent-cdg4-1.xx&_nc_gid=l1Bh9p59OTLo4aZO-Wub4A&_nc_ss=7b289&oh=00_Af-Fm6dDtZVU8hSj4iDa2occVlPZb24GcLOy42UbwRYNPQ&oe=6A3AD109",
    "date": "Fri, 12 Jun 2026 10:45:40 GMT"
  },
  {
    "market": "Boulevard",
    "source": "boulevard",
    "title": "👔💙 𝐇𝐚𝐩𝐩𝐲 𝐅𝐚𝐭𝐡𝐞𝐫❜𝐬 𝐃𝐚𝐲💙👔 Today, we celebrate the strength, love, and sacrifices of all fathers and fat...",
    "link": "https://m.facebook.com/permalink.php?id=100054502119213&story_fbid=pfbid02oE2E6Eefsnp592sSS7cbC1HiEZy2f55Lqr9EtyLsu9F85ZHsZofgU7w3ZNwPNnJTl",
    "image": "https://scontent-sjc3-1.xx.fbcdn.net/v/t39.30808-6/724376247_1534687741691282_2838533872208824217_n.jpg?_nc_cat=110&ccb=1-7&_nc_sid=ebae6b&_nc_ohc=HyduAzU2f84Q7kNvwHuOWWe&_nc_oc=AdqEbNcmHTQ4iH-yN8rrlfKnsS5DhOLVhOch8799TlAXJJYIQUahKdXFYUhXQwSpc0c&_nc_zt=23&_nc_ht=scontent-sjc3-1.xx&_nc_gid=Q1JPA_KwmXJ2mdPmH7x1kA&_nc_ss=7b289&oh=00_Af9us9VJS9ZFYLZ5sBWxTholuczDzSrqIScR-3Vvsa2Fkw&oe=6A3F9A17",
    "date": "Sun, 21 Jun 2026 02:01:03 GMT"
  },
  {
    "market": "Boulevard",
    "source": "boulevard",
    "title": "🐉 Happy Dragon Boat Festival! 🛶 Wishing everyone a joyful celebration filled with happiness, good health, and deliciou...",
    "link": "https://m.facebook.com/permalink.php?id=100054502119213&story_fbid=pfbid02bVyDvzGy5cdUFH9E1ims6H3QB8z7pcGgY2UdRmZDii8yDB8uY6PJMv5dtR6TTgMul",
    "image": "https://scontent-sjc3-1.xx.fbcdn.net/v/t39.30808-6/724143231_1536405454852844_2496970215832925135_n.jpg?_nc_cat=103&ccb=1-7&_nc_sid=ebae6b&_nc_ohc=J1d-Tb8RIDkQ7kNvwGPIvgn&_nc_oc=AdqgMECuyh10r_38-oZi7noylftlgiDuj-kOrmp4xV2e6ecJJcdw2OQPZT8OpX4NPr8&_nc_zt=23&_nc_ht=scontent-sjc3-1.xx&_nc_gid=Q1JPA_KwmXJ2mdPmH7x1kA&_nc_ss=7b289&oh=00_Af9_mCb-BDs0eGlkN-kXZPi0iiR3XD3wEOY2ePinJbUvNw&oe=6A3F68DA",
    "date": "Fri, 19 Jun 2026 02:01:02 GMT"
  },
  {
    "market": "Boulevard",
    "source": "boulevard",
    "title": "🛒 𝐖𝐄𝐄𝐊𝐋𝐘 𝐒𝐀𝐕𝐄𝐑𝐒 𝐀𝐑𝐄 𝐇𝐄𝐑𝐄🎉 Don't miss out on amazing deals and great savings on your everyday essent...",
    "link": "https://m.facebook.com/permalink.php?id=100054502119213&story_fbid=pfbid02ER32ikPo2x5MHzfM6L2x1bc32TeXkYjUWi37NGQBGsWgKh58yhqkRrP962zVkvX3l",
    "image": "https://scontent-sjc3-1.xx.fbcdn.net/v/t39.30808-6/727323583_1535918001568256_1582065413313130564_n.jpg?stp=dst-jpg_p526x296_tt6&_nc_cat=110&ccb=1-7&_nc_sid=e5c1b6&_nc_ohc=jppDV-EUoz8Q7kNvwGXPQnQ&_nc_oc=AdoTQrYIw8A0R_LETPZWFrSNGxdDDhjPPHHZq3RPSUJMdk0ijYLZMwH0rZRZWn6IRio&_nc_zt=23&_nc_ht=scontent-sjc3-1.xx&_nc_gid=Q1JPA_KwmXJ2mdPmH7x1kA&_nc_ss=7b289&oh=00_Af94KQCk9MPea-4Ou2hXgCi72uAeqg7dOT-HiFc-HgZMpA&oe=6A3F88C9",
    "date": "Thu, 18 Jun 2026 10:12:02 GMT"
  },
  {
    "market": "Boulevard",
    "source": "boulevard",
    "title": "🎉🔥 𝟔𝟏𝟖 𝐒𝐏𝐄𝐂𝐈𝐀𝐋 𝐎𝐅𝐅𝐄𝐑 𝐈𝐒 𝐇𝐄𝐑𝐄🔥🎉 Get ready for amazing deals and incredible savings this 𝟭𝟴𝘁𝗵...",
    "link": "https://m.facebook.com/permalink.php?id=100054502119213&story_fbid=pfbid02NWCfpB6VULbypz9xA2jXtaJ4FurarJpNFYHJWTL9tHMWrgeeDAbD4B6cVEfeNNJsl",
    "image": "https://scontent-mia5-1.xx.fbcdn.net/v/t39.30808-6/725083973_1534984464994943_2334963569628614646_n.jpg?stp=dst-jpg_p526x296_tt6&_nc_cat=102&ccb=1-7&_nc_sid=e5c1b6&_nc_ohc=yv9GRMeqhq4Q7kNvwEAjN2Q&_nc_oc=AdqznGpoBIaeonfwVuIM4Sak1MG4TG9n3B0fBbzTESsv2w1LE0kJaPtAvVKxJN7eqmI&_nc_zt=23&_nc_ht=scontent-mia5-1.xx&_nc_gid=o3wshK7zrt1lzgUPxrgWaQ&_nc_ss=7b289&oh=00_Af9ysIdgZhtMiqLq3Z8loaK_EX-XutyTIjhcENCftKoj7w&oe=6A3E538D",
    "date": "Wed, 17 Jun 2026 10:00:13 GMT"
  },
  {
    "market": "Doremart",
    "source": "doremart",
    "title": "HAPPY MORNING 🎉 Visit #DoremartBintulu 23 JUNE 2026 (9.00AM-12.00PM) Business Hour: 8.00AM - 9.30PM 📍Location: LOT 419...",
    "link": "https://m.facebook.com/DoremartBintulu/posts/pfbid02iyyMW6WdwPP2W2p5dxx4b6sJDSVwBbWpxNTFU2CstoUUVT8KZCtykMjbcarYqBNil",
    "image": "https://scontent-ams2-1.xx.fbcdn.net/v/t39.30808-6/727434176_989394363842967_489585891048927717_n.jpg?stp=dst-jpg_s720x720_tt6&_nc_cat=103&ccb=1-7&_nc_sid=e5c1b6&_nc_ohc=wH7CdXN576MQ7kNvwEHBjlr&_nc_oc=Adq1kQglMJNRtb0QXO-T1L6YQnrzGHIaZ4RqEYsabS_u3Mpl2e01xEhbdPJ3rX8alsBe_meIirtrZ7bDmYAgbPXb&_nc_zt=23&_nc_ht=scontent-ams2-1.xx&_nc_gid=s1FT3dsIf7UA9_HGue4wBQ&_nc_ss=7b289&oh=00_Af-3ewLyBZgd_uXVjoNuPVM9VaiNIi8OPr1elul_F3MnVQ&oe=6A3F742B",
    "date": "Mon, 22 Jun 2026 07:56:12 GMT"
  },
  {
    "market": "Doremart",
    "source": "doremart",
    "title": "HAPPY HOUR🎉 Visit #DoremartBintulu 22 JUNE 2026 (3.00PM-6.00PM) Business Hour: 8.00AM - 9.30PM 📍Location: LOT 419 & LO...",
    "link": "https://m.facebook.com/DoremartBintulu/posts/pfbid02tj2S8hWZKeFEruFASEdi1q6WM51YmG2Dvaf7YCpsMwZrZrN9uduhyu2RHzfG8ibkl",
    "image": "https://scontent-ams2-1.xx.fbcdn.net/v/t39.30808-6/728544027_989352103847193_8751349480397996924_n.jpg?stp=dst-jpg_s720x720_tt6&_nc_cat=101&ccb=1-7&_nc_sid=e5c1b6&_nc_ohc=uAsXzfEu-KYQ7kNvwHkSlDu&_nc_oc=AdobawoEkEHwsx4bBvIxDPXPRTUYmH90Y6zjRERZ9V4fQdUHVSB76wiS3kMwci4VDLQrpGIgxnd6DCLSnmASOhOn&_nc_zt=23&_nc_ht=scontent-ams2-1.xx&_nc_gid=s1FT3dsIf7UA9_HGue4wBQ&_nc_ss=7b289&oh=00_Af-ISt3uYEtPaFGC2km5PnPIvrITue9CrQij90loLvnb6Q&oe=6A3F739C",
    "date": "Mon, 22 Jun 2026 06:06:58 GMT"
  },
  {
    "market": "Doremart",
    "source": "doremart",
    "title": "🎉✨ PURCHASE WITH PURCHASE! ✨🎉 📅22-28 JUNE 2026 📍Doremart Bintulu Anda boleh jimat lebih dengan tawaran PWP (Purchase...",
    "link": "https://m.facebook.com/DoremartBintulu/posts/pfbid037WTCZNmQBgEpvcpHcSjcED9kvp5dFR84W9vDsAeUFXAA9w7YLSusn3CVFv9Ceo8al",
    "image": "https://scontent-ams2-1.xx.fbcdn.net/v/t39.30808-6/727542955_988610123921391_6709363017464168146_n.jpg?stp=dst-jpg_p720x720_tt6&_nc_cat=109&ccb=1-7&_nc_sid=e5c1b6&_nc_ohc=v4tua6dJBmMQ7kNvwENFHcQ&_nc_oc=AdrVtWeSvjYxsAvnEDNKNPPWdWwWBDyiB6AB3TXIe0iR8HI6EaljKeUe6EtRgjT4NaOm1r6aVRWzNAExXd7ZMaob&_nc_zt=23&_nc_ht=scontent-ams2-1.xx&_nc_gid=s1FT3dsIf7UA9_HGue4wBQ&_nc_ss=7b289&oh=00_Af8-Iq8wAPJAx-HTygz5d9zGcTdt1MPt0WUKTUQras_qwQ&oe=6A3F7AF8",
    "date": "Sun, 21 Jun 2026 11:16:01 GMT"
  },
  {
    "market": "Doremart",
    "source": "doremart",
    "title": "🛒 PROMOSI BIJAK BERBELANJA 💡省钱有妙招，生活没烦恼! 💡 📅 Tarikh:  22-25 JUNE 2026 📍 Tempat:  Doremart Bintulu Nak jimat poket t...",
    "link": "https://m.facebook.com/DoremartBintulu/posts/pfbid02fBFuz2uv2GrgFKHCDe57CG1Ap2yLYHdJcvtrJ2voTtdUjJFis8NvhcmiGKCBSxqLl",
    "image": "https://scontent-ams2-1.xx.fbcdn.net/v/t39.30808-6/726997992_989198193862584_7491401131926782507_n.jpg?stp=dst-jpg_p526x296_tt6&_nc_cat=105&ccb=1-7&_nc_sid=e5c1b6&_nc_ohc=HdVUosID_-oQ7kNvwEnGRrY&_nc_oc=AdofC6d5KptwW6LVb4vOdFKnysgMQJOubuEirGzc-Mt96uZszEIv61RBDwy2N7tJSCYMuNKQ5leaQ0LcnGDyKC8U&_nc_zt=23&_nc_ht=scontent-ams2-1.xx&_nc_gid=s1FT3dsIf7UA9_HGue4wBQ&_nc_ss=7b289&oh=00_Af9O7jQMbggeUhlpUwnt2ZbNg8xX04S66zUCTeUPf5daLQ&oe=6A3F80DC",
    "date": "Sun, 21 Jun 2026 11:14:01 GMT"
  },
  {
    "market": "Doremart",
    "source": "doremart",
    "title": "BEST VALUE COMBO 🥛🍪 Gandingan mantap Dutch Lady Full Cream (1L) + Biskut Kelapa Roma (300g) untuk korang! Lebih jimat,...",
    "link": "https://m.facebook.com/DoremartBintulu/posts/pfbid02TJoCnR4faq1VGScH6fAGXfXcErYYwednSxVoN5pqtLYHNtMigDoTKYSaw5DFbqjnl",
    "image": "https://scontent-ams2-1.xx.fbcdn.net/v/t39.30808-6/727466519_988611383921265_7077426892347906936_n.jpg?stp=dst-jpg_s1080x2048_tt6&_nc_cat=105&ccb=1-7&_nc_sid=ebae6b&_nc_ohc=w39oxm2iPusQ7kNvwG1RdAv&_nc_oc=AdoSyjI9SV-apNPoHRC5F0Vi48o07kNaFvryxgIOR8pZV5TrlxrlxE3SdSeFxjB-8wGeV8_-0GjoLXLP2ymacmEN&_nc_zt=23&_nc_ht=scontent-ams2-1.xx&_nc_gid=s1FT3dsIf7UA9_HGue4wBQ&_nc_ss=7b289&oh=00_Af-zPwhOTd9LhB0jgMyEKZVXoA5gYA6KqYATDsJx9ld10Q&oe=6A3F8D9C",
    "date": "Sun, 21 Jun 2026 10:14:47 GMT"
  },
  {
    "market": "Doremart",
    "source": "doremart",
    "title": "FREE TELUR AYAM HARI INI SAJA! 🥚✨ Sempena Hari Bapa, Jom serbu Doremart sekarang! Belanja minimum RM100 dalam satu resi...",
    "link": "https://m.facebook.com/DoremartBintulu/posts/pfbid02fZRn8QmGKbGgSYFRQuFjyQpCPZzCebVdpqo3qncgUenvPtU2VGxDteqvSS5pSLHpl",
    "image": "https://scontent-cdg4-2.xx.fbcdn.net/v/t39.30808-6/727737634_1488403993320195_4593101130165862207_n.jpg?stp=dst-jpg_p180x540_tt6&_nc_cat=100&ccb=1-7&_nc_sid=e5c1b6&_nc_ohc=5RSp4Q7BQxQQ7kNvwHti2vg&_nc_oc=AdpNIJ0l--rOetA2yncMmxGUDpiK_l0deNAySRCERO8gkfC0bM1_2cK1yPo438VlcMo&_nc_zt=23&_nc_ht=scontent-cdg4-2.xx&_nc_gid=UcxPHQQSsqJSg4FrrIjZsQ&_nc_ss=7b289&oh=00_Af-5CIZzXP_hRFJdGi4PA-UbsFeoNKIQSnIr0XWSdMnhYA&oe=6A3E9E09",
    "date": "Sun, 21 Jun 2026 08:20:33 GMT"
  },
  {
    "market": "Doremart",
    "source": "doremart",
    "title": "HAPPY MORNING 🎉 Visit #DoremartBintulu 22 JUNE 2026 (9.00AM-12.00PM) Business Hour: 8.00AM - 9.30PM 📍Location: LOT 419...",
    "link": "https://m.facebook.com/DoremartBintulu/posts/pfbid0LwfiNcxb87dmWkqZCdNgZbBvyx14z9KxFAtNkLnmPjzUF9tQtKWYtdBLmYa7snQ7l",
    "image": "https://scontent-fra3-1.xx.fbcdn.net/v/t39.30808-6/727446613_988535253928878_4940329818285828872_n.jpg?stp=dst-jpg_s720x720_tt6&_nc_cat=103&ccb=1-7&_nc_sid=e5c1b6&_nc_ohc=v5P_TY_wHRgQ7kNvwHvTVxo&_nc_oc=AdqCSgMZcfPEStro4-3wZxLTulNGdrcy_Ar3S6ziUG0yKO_uXBdYdkTF_FX3rcnqkOjHCLO9v2Rfp1RyQd-PN-cr&_nc_zt=23&_nc_ht=scontent-fra3-1.xx&_nc_gid=ZpmwNG1tQ5SfaDDWqhalaw&_nc_ss=7b289&oh=00_Af-M2L-czWurq0kZHx3Is0c6c0n1BbpjpmHFluclylnT5g&oe=6A3DA72C",
    "date": "Sun, 21 Jun 2026 08:12:00 GMT"
  },
  {
    "market": "Doremart",
    "source": "doremart",
    "title": "HAPPY HOUR🎉 Visit #DoremartBintulu 21 JUNE 2026 (3.00PM-6.00PM) Business Hour: 8.00AM - 9.30PM 📍Location: LOT 419 & LO...",
    "link": "https://m.facebook.com/DoremartBintulu/posts/pfbid023J3MK2ZwvWUFpS74JpPReiVo1KHzqU18VcFTbsGsSpegQ6jZMUDGKrkc2h4Nh16Tl",
    "image": "https://scontent-den2-1.xx.fbcdn.net/v/t39.30808-6/727346826_988437240605346_6785766083827083640_n.jpg?stp=dst-jpg_s720x720_tt6&_nc_cat=108&ccb=1-7&_nc_sid=e5c1b6&_nc_ohc=hnCwSq0EXBAQ7kNvwHSZFI4&_nc_oc=AdqR3RFymy1KPjvb8JoDssrqo494Rc2Oux5pVgyTPHE2J6K6PA4BlMN7mQ28ocTp3v0&_nc_zt=23&_nc_ht=scontent-den2-1.xx&_nc_gid=84g1FACPh7eWF1jedrYE0g&_nc_ss=7b289&oh=00_Af8pOlBWvo-GtZIeLCVLKI6DZFaeBX4wd-mYRa48_4zbFw&oe=6A3D81D4",
    "date": "Sun, 21 Jun 2026 05:31:46 GMT"
  },
  {
    "market": "New World Mart",
    "source": "newworld",
    "title": "Photos from NEW WORLD MART, BINTULU's post",
    "link": "https://www.facebook.com/1185712486933399/posts/1435485301956115",
    "image": "https://scontent-cdg4-3.xx.fbcdn.net/v/t39.30808-6/725690061_1435483725289606_4816296994609284653_n.jpg?stp=dst-jpg_s720x720_tt6&_nc_cat=111&ccb=1-7&_nc_sid=127cfc&_nc_ohc=BSjq7L_IBysQ7kNvwEUah9I&_nc_oc=Ado9j0Ahjh6aJsPuHPI-XwYG-dg4sa8KK2zsQLLbXSLj7Jf-4Lz2C7QEm3OkZpGTSOE&_nc_zt=23&_nc_ht=scontent-cdg4-3.xx&edm=AJdBtusEAAAA&_nc_gid=fd1KaJiAEwWQa_K6CnWOCw&_nc_tpa=Q5bMBQH06rGHecYrTrkD-uCnP0kJxkAduu8KgJwbhM4ZDXq1rslAkKBP4tyKJgEtjrKi1tlP9pBxl5uZ&oh=00_Af-ONEykdqe_mvbieHcWGROZF-mJ_LYNmen0brbk9ZzmiQ&oe=6A3DF67D",
    "date": "Sat, 20 Jun 2026 01:23:42 +0000"
  },
  {
    "market": "New World Mart",
    "source": "newworld",
    "title": "Photos from NEW WORLD MART, BINTULU's post",
    "link": "https://www.facebook.com/1185712486933399/posts/1434027428768569",
    "image": "https://scontent-cdg4-2.xx.fbcdn.net/v/t39.30808-6/725113014_1434025022102143_450277408814351257_n.jpg?stp=dst-jpg_s720x720_tt6&_nc_cat=107&ccb=1-7&_nc_sid=127cfc&_nc_ohc=xv8JK2I6XfQQ7kNvwGZ_Bke&_nc_oc=Ado19eULVAVYtqFYwFc4rc1YX9VyQg2zC7YtsDz5540rR3iUbB-hTk9YkccxfhHSkr4&_nc_zt=23&_nc_ht=scontent-cdg4-2.xx&edm=AJdBtusEAAAA&_nc_gid=fd1KaJiAEwWQa_K6CnWOCw&_nc_tpa=Q5bMBQFp1FDNdEOlh0YfORtnZmNn8N7gD6xBi3HIPa9M37jz815ByqywuACpF9OqktRWVRXLCYc2QQYy&oh=00_Af9ajRgcC1cXV7Ysms9Q0zu9KhLgAiq1mk6vcxQhpv6qsA&oe=6A3E020B",
    "date": "Thu, 18 Jun 2026 20:15:01 +0000"
  },
  {
    "market": "New World Mart",
    "source": "newworld",
    "title": "Photos from NEW WORLD MART, BINTULU's post",
    "link": "https://www.facebook.com/1185712486933399/posts/1433993135438665",
    "image": "https://scontent-cdg4-2.xx.fbcdn.net/v/t39.30808-6/723119961_1433989728772339_1759192517658176054_n.jpg?stp=dst-jpg_s720x720_tt6&_nc_cat=109&ccb=1-7&_nc_sid=127cfc&_nc_ohc=hLOq4fiUvv4Q7kNvwGSVx3r&_nc_oc=AdpjSvI7xjiARj5zLjy6I1Bnsp_9EpTpCeEoE5Bt6JIKyyliYp0Rqn9dBhDVvgCHYd0&_nc_zt=23&_nc_ht=scontent-cdg4-2.xx&edm=AJdBtusEAAAA&_nc_gid=fd1KaJiAEwWQa_K6CnWOCw&_nc_tpa=Q5bMBQHm0COO-Bh2VITNk7Rj_yx8qc7pEF4YeqbkNTzd3sVsVoau686-n8Rplb0j5ga5xYjSZOuiuOuE&oh=00_Af-5kpdSfrwsOeMkLLr0VuHQ6oGc9ouADIOZOebaVL-IZA&oe=6A3DFEB9",
    "date": "Thu, 18 Jun 2026 08:15:01 +0000"
  },
  {
    "market": "Farley",
    "source": "farley",
    "title": "🐟 新鲜到货！挪威全条三文鱼 🇳🇴 ​Farley Bintulu 带来顶级美味！Fresh Norway Whole Salmon 肥美到货，全条现货，数量有限，手慢无！ ​💰 心动特价：只需 RM69.90 / KG 无论是做刺...",
    "link": "https://m.facebook.com/FarleyBintulu.OfficialPage/posts/pfbid09t4LxiFZ7aSn2e8QBanUg2bF32KwCh59CjViMKitj1GcZcF7v8ipx8ZcUhwkqeV7l",
    "image": "https://scontent-ams2-1.xx.fbcdn.net/v/t39.30808-6/725182115_1327862789463344_4919353278412594748_n.jpg?stp=dst-jpg_p552x414_tt6&_nc_cat=110&ccb=1-7&_nc_sid=e21142&_nc_ohc=-EhxvGUEaagQ7kNvwHWZwhL&_nc_oc=AdoYrABoNjzhiBdfju0V27veYHB7ZIxgpucBFTL0CI3duufVqrP5TRa4_zPFceDyEda7xCTwKBSwQeBSwjV04kGF&_nc_zt=23&_nc_ht=scontent-ams2-1.xx&_nc_gid=4xb2Y7KxfXogPMgcDwE8Yg&_nc_ss=7b289&oh=00_Af8t1kQEXVz1rPFJ3OTXdGF3-58M6aAKjHDL2PfF9z3Ttw&oe=6A3F76D5",
    "date": "Wed, 17 Jun 2026 00:49:46 GMT"
  },
  {
    "market": "Econsave",
    "source": "econsave ",
    "title": "🛒 JOM JIMAT DI ECONSAVE! 🛒 Jangan lepaskan peluang menikmati harga penjimatan yang berbaloi untuk keperluan harian and...",
    "link": "https://m.facebook.com/EconsaveMBBK/posts/pfbid0T1S9pebmEzunRS7YZt6g1quNG8ykse2HMWLVkDuCKJvSiVRW78XRZtw4s51K1deql",
    "image": "https://scontent-cdg4-1.xx.fbcdn.net/v/t39.30808-6/729746963_1420159120138487_8637858992414358591_n.jpg?stp=dst-jpg_s720x720_tt6&_nc_cat=104&ccb=1-7&_nc_sid=e21142&_nc_ohc=Qw2BGJN3X-MQ7kNvwHMWDSZ&_nc_oc=AdqSPe55MyLG0Zqj6o5pZJ5FkblC7Cx1Qza8A2Xeh3wLPDM57EKGivzo_ShyvjLo1w0&_nc_zt=23&_nc_ht=scontent-cdg4-1.xx&_nc_gid=YlVMKraEpIjhGCqZW6_X5g&_nc_ss=7b289&oh=00_Af-An3GXQGFKoCDtpemEui61irtiN4rJsgBz3UMn4kDOuw&oe=6A3F7A25",
    "date": "Mon, 22 Jun 2026 12:52:56 GMT"
  },
  {
    "market": "Econsave",
    "source": "econsave ",
    "title": "JOMMMM‼️‼️ WARGA MIRI, MASA UNTUK BORONGGGG 😍💥 PROMOSI SEGAR & MURAH + JOM JIMAT dah start ni!! Nak masak sedap? Nak j...",
    "link": "https://m.facebook.com/EconsaveMBBK/posts/pfbid0Jyepj31suVNXcbLrt4rpzyUow3Zg1gLdfm2F36RvJRF15kbJc7st2qSvNcwBzUhWl",
    "image": "https://scontent-cdg4-2.xx.fbcdn.net/v/t39.30808-6/727304499_1417949337026132_1166441509291730466_n.jpg?stp=dst-jpg_s720x720_tt6&_nc_cat=107&ccb=1-7&_nc_sid=e21142&_nc_ohc=_Au-k_fhiYAQ7kNvwFGKv1M&_nc_oc=Adp3GwWgzhHsdUGV0n2DdgCmxngfJ5sv66lpiGU-_tSLYImIOi-sLRS8bBiC42jisEc&_nc_zt=23&_nc_ht=scontent-cdg4-2.xx&_nc_gid=YlVMKraEpIjhGCqZW6_X5g&_nc_ss=7b289&oh=00_Af-knvaLEq1PSPwWKjvF7Dl0heije7f1zPHOAnACKPRqtQ&oe=6A3F72B6",
    "date": "Sat, 20 Jun 2026 00:30:17 GMT"
  },
  {
    "market": "Econsave",
    "source": "econsave ",
    "title": "🥳WEEKEND JIMAT GILA🥳 ECONSAVE jimat poket, hati pun senang.  Jom!! Penuhkan bakul dengan barangan keperluan ✅Keperluan...",
    "link": "https://m.facebook.com/EconsaveMBBK/posts/pfbid02LtAwDgGY9NAHLya2N4AthzBSpz16evqnqrXp4kFanKxmEU3X7fvWCV3o7kChcnhfl",
    "image": "https://scontent-cdg4-2.xx.fbcdn.net/v/t39.30808-6/727339423_1417946150359784_3571482631577838346_n.jpg?stp=dst-jpg_s720x720_tt6&_nc_cat=107&ccb=1-7&_nc_sid=e21142&_nc_ohc=FyD2Th_HNTQQ7kNvwG8nDQw&_nc_oc=Adr8IKqz6FqQA3OUWy03xyaqLsdf9NsmvEk7UwquH84pTF84BtmrRrYaTz8fgL38hUo&_nc_zt=23&_nc_ht=scontent-cdg4-2.xx&_nc_gid=YlVMKraEpIjhGCqZW6_X5g&_nc_ss=7b289&oh=00_Af-E41f_fnumLjj28JCIvp9kVzht6ZAfCv7wDVDWR54BFg&oe=6A3F99FD",
    "date": "Fri, 19 Jun 2026 23:46:07 GMT"
  },
  {
    "market": "Econsave",
    "source": "econsave ",
    "title": "💥 JUALAN RAHMAH Econsave Bintangor Kembali Lagi! 💥 Jom nikmati penjimatan lebih hebat pada 20 & 21 Jun! 🛒✨ Pelbagai b...",
    "link": "https://m.facebook.com/EconsaveMBBK/posts/pfbid05VpMnuEDsR4bzDiemqM4TNVavKcKXPS6SRCPioZSTH7yeAqRfaUtpfjvRYcmSvqFl",
    "image": "https://scontent-fra5-2.xx.fbcdn.net/v/t39.30808-6/727304500_1417457197075346_8558531891219327006_n.jpg?stp=dst-jpg_s720x720_tt6&_nc_cat=106&ccb=1-7&_nc_sid=e21142&_nc_ohc=XRRWbUA6QuYQ7kNvwHBxZZA&_nc_oc=Adro_GkPX9LVywHvTN2BFrO9Y28V4MhBkNhfjWvYcBHxPHeYvD2ikSgjMo8HlKde1j8WHRoMdJm9wdmheSXVtjam&_nc_zt=23&_nc_ht=scontent-fra5-2.xx&_nc_gid=RxH9IQuJQby8x8nwgcfqNw&_nc_ss=7b289&oh=00_Af_h1TnY1D_gRnh8QykcoQTkJZuVJ1JsH5z9RIJ6wVRrAg&oe=6A3EEAAB",
    "date": "Fri, 19 Jun 2026 10:39:37 GMT"
  },
  {
    "market": "Econsave",
    "source": "econsave ",
    "title": "JOM JIMAT DI ECONSAVE SARAWAK! 🔥 Harga memang nang antap gilak! 💥 Mun nak jimat, sik payah pikir panjang — terus datan...",
    "link": "https://m.facebook.com/EconsaveMBBK/posts/pfbid02Qaswp85TKTxE6goPUZvZgdEZEXjuFSZjQrPmJ618darQcJWfr9cN8gy7Bx3HKVkfl",
    "image": "https://scontent-den2-1.xx.fbcdn.net/v/t39.30808-6/726367969_1416719457149120_8662575814370269431_n.jpg?stp=dst-jpg_p843x403_tt6&_nc_cat=110&ccb=1-7&_nc_sid=2e5b1e&_nc_ohc=N849PIVJ2mwQ7kNvwFaTzq-&_nc_oc=AdrnugvhqGCpeAzjC-iJANypIiD1wMoXKFdvjTWGLNgSpKMiuvL2st7q0g9Slji8nYw&_nc_zt=23&_nc_ht=scontent-den2-1.xx&_nc_gid=bb5k6Hb05c145nJvEaSEWQ&_nc_ss=7b289&oh=00_Af9VrGiSevSp74A7ziApGMvu9RbTaGaTUsRHx3ouIbx42g&oe=6A3CDA45",
    "date": "Fri, 19 Jun 2026 00:00:32 GMT"
  },
  {
    "market": "SING KWONG",
    "source": "singkwong",
    "title": "Great news dear customers! Our * WEEKEND SALES 2026* is here !!!🤩😍😍😍😍 📌Great Deals! Great Variety! Limited Time!...",
    "link": "https://m.facebook.com/permalink.php?id=100076005246080&story_fbid=pfbid02xAzFk5WbebLDAF1YYCDTx88uZ5RY2yMGN5y5V8edKNnF4qLM2Qc61p6oqThV62UAl",
    "image": "https://scontent-atl3-1.xx.fbcdn.net/v/t39.30808-6/726337522_1035383129005186_4800859946133995204_n.jpg?stp=dst-jpg_p320x320_tt6&_nc_cat=100&ccb=1-7&_nc_sid=e21142&_nc_ohc=jCtU6FlRX74Q7kNvwEnMigL&_nc_oc=Adr8nAmfAEE3idl5REa4JQEou8Bm5eKxVaDEuwxo1RZa_u_ey-xIc8jKy47Ipm0_P-k&_nc_zt=23&_nc_ht=scontent-atl3-1.xx&_nc_gid=mtITOa0gCU-vNXqjEaEA-g&_nc_ss=7b289&oh=00_Af933oeSCktXaQ0usa0ZlOCxwLptBlcORxU0UY0jMV1D6w&oe=6A3F8486",
    "date": "Fri, 19 Jun 2026 13:13:45 GMT"
  },
  {
    "market": "Everwin Supermarket",
    "source": "everwin",
    "title": "“Ingat Everwin, ingat murah!”  Weekend sales start on 19/06/26-21/06/26 🤩  Don’t miss out & happy shopping! ✨🛒 #everwi...",
    "link": "https://m.facebook.com/permalink.php?id=100064802376551&story_fbid=pfbid0Zs4rJrfsvDXtmL8feJti7uV57HL2fN76ZUXhgFa9KWiEtheSCG89Pawq8BZvkPE4l",
    "image": "https://scontent-hou1-1.xx.fbcdn.net/v/t39.30808-6/727268482_1444166521086747_6763215997621576057_n.jpg?stp=dst-jpg_s720x720_tt6&_nc_cat=100&ccb=1-7&_nc_sid=e21142&_nc_ohc=IAnanJNWy4cQ7kNvwGOHool&_nc_oc=AdqvVKHzwuY-eWILxMVPHmcC9tMYQy-qsLiKA4QizbYWQIQr-CssfHd9boEwwXuaXY8&_nc_zt=23&_nc_ht=scontent-hou1-1.xx&_nc_gid=muyc5_R9bfma_xoailwWhg&_nc_ss=7b289&oh=00_Af8poupvyw02fb8mc_giwN6Tw0UWfU5daBx0MiTkxjrJAg&oe=6A3F73DD",
    "date": "Thu, 18 Jun 2026 14:55:21 GMT"
  },
  {
    "market": "Everwin Supermarket",
    "source": "everwin",
    "title": "“Ingat Everwin, ingat murah!”  Weekend sales start on 12/06/26-14/06/26 🤩  Don’t miss out & happy shopping! ✨🛒 #everwi...",
    "link": "https://m.facebook.com/permalink.php?id=100064802376551&story_fbid=pfbid09tGzHt818avA8hUNZGqBdErwKUoaZYjNq8U4yYhvVzEfjDLMhTHV9qn9b8a9BKFUl",
    "image": "https://scontent-hou1-1.xx.fbcdn.net/v/t39.30808-6/721403377_1437814221721977_5846620078161389222_n.jpg?stp=dst-jpg_s720x720_tt6&_nc_cat=102&ccb=1-7&_nc_sid=e21142&_nc_ohc=7vt9tDBG73oQ7kNvwGppqFi&_nc_oc=AdrSeOaAQHKIVx6erCMx6otOCzIAhag-XPGVu5gxEkITZovd8AdLbdq3SMauBMDSqsc&_nc_zt=23&_nc_ht=scontent-hou1-1.xx&_nc_gid=muyc5_R9bfma_xoailwWhg&_nc_ss=7b289&oh=00_Af-KJVtLY5ot5jUpCy_iGz4c89VOSwsFuxAd3wFTPQu8Uw&oe=6A3F6C6A",
    "date": "Thu, 11 Jun 2026 13:33:06 GMT"
  },
  {
    "market": "Everwin Supermarket",
    "source": "everwin",
    "title": "𝓢𝓮𝓵𝓪𝓶𝓪𝓽 𝓗𝓪𝓻𝓲 𝓖𝓪𝔀𝓪𝓲 2026 🌾 Don’t miss out Everwin supermarket gawai sales✨ Let’s celebrate gawai with us...",
    "link": "https://m.facebook.com/permalink.php?id=100064802376551&story_fbid=pfbid02ZG1WxaW4UjdyzPqLzr18HoC8gzWXBvyh1RNhJup5su7NApUo9GP3AGixPCg6y8FBl",
    "image": "https://scontent-hou1-1.xx.fbcdn.net/v/t39.30808-6/707370645_1423098223193577_5346432446263012804_n.jpg?stp=dst-jpg_s720x720_tt6&_nc_cat=101&ccb=1-7&_nc_sid=e21142&_nc_ohc=VOcs3P3rXswQ7kNvwFUu1m9&_nc_oc=Adr473mOx8tytFGtHAKn933q25ImeqKBp_P2CNnl-dPxY9F2zNJq_T2w6J_7RXJS7ro&_nc_zt=23&_nc_ht=scontent-hou1-1.xx&_nc_gid=muyc5_R9bfma_xoailwWhg&_nc_ss=7b289&oh=00_Af8UiQVd8xMi-bZ31JbG6R_MVyPNI3HErpt_2rqqqC4isA&oe=6A3F964C",
    "date": "Wed, 27 May 2026 00:01:35 GMT"
  },
  {
    "market": "Everwin Supermarket",
    "source": "everwin",
    "title": "🛍 🛒 Program Jualan RAHMAH MADANI Hari Gawai akan diadakan seperti ketetapan di bawah: 🏬Tempat: Everwin Supermarket Bi...",
    "link": "https://m.facebook.com/permalink.php?id=100064802376551&story_fbid=pfbid0waG3UrQRrrpw19p9fpm8uLyGCRZELZWLSdWD7q7ehqHGFAp4Kt2QhXRKmNkHmo8wl",
    "image": "https://scontent-hou1-1.xx.fbcdn.net/v/t39.30808-6/702043448_1417407920415298_8169743205312561701_n.jpg?_nc_cat=106&ccb=1-7&_nc_sid=e21142&_nc_ohc=vm57waRHEbQQ7kNvwEjG74h&_nc_oc=Adq47BmDOHXLYFhkSk9WWSOrSqfJ3-rRvcWWvb_QLZUAy1QzrgDzsUlXih_7eC6jl2Q&_nc_zt=23&_nc_ht=scontent-hou1-1.xx&_nc_gid=muyc5_R9bfma_xoailwWhg&_nc_ss=7b289&oh=00_Af_V1Cg-twdqAu7JjvgHoeMS8IZuClQr6ve1naZBx6E7yQ&oe=6A3F9E07",
    "date": "Wed, 20 May 2026 08:43:40 GMT"
  },
  {
    "market": "Everwin Supermarket",
    "source": "everwin",
    "title": "📢📢 Hai Mama & Papa di Sabah & Sarawak! Selamat Tadau Kaamatan dan Hari Gawai bersama Dugro® dengan 3X Penyerapan Zat B...",
    "link": "https://m.facebook.com/permalink.php?id=100064802376551&story_fbid=pfbid05p49HWdV4tzRYExnSYTzbSt4VfKXHdAjMPdxBXDMyTqyRKSpMS79saJDGGWa3GQkl",
    "image": "https://scontent-hou1-1.xx.fbcdn.net/v/t39.30808-6/702903145_1417290363774363_8807941318423073724_n.jpg?stp=dst-jpg_p960x960_tt6&_nc_cat=102&ccb=1-7&_nc_sid=2e5b1e&_nc_ohc=wOW2CsZHpgIQ7kNvwFFptdY&_nc_oc=Adq9lU0DBOZCmvX849JIbpxZmT-rWCLbfcGHEmBNwkkGqbBwZ7ihgFBdCAJcpEpF5XM&_nc_zt=23&_nc_ht=scontent-hou1-1.xx&_nc_gid=muyc5_R9bfma_xoailwWhg&_nc_ss=7b289&oh=00_Af-BazuDVjgpvNOaaBjPmiDLLbw0bEMt4bE9epg6YonyAA&oe=6A3F7DED",
    "date": "Wed, 20 May 2026 08:43:11 GMT"
  },
  {
    "market": "MDS",
    "source": "mds",
    "title": "🎉 MDS MEDAN JUALAN RAHMAH 🎉 Berita baik untuk semua pelanggan setia! ✨ Nikmati pelbagai barangan keperluan harian pada...",
    "link": "https://m.facebook.com/mdsmartofficial/posts/pfbid031gLWXSpxGrfNwhU4dhfQP5KhVK14D5hGtCEdWzsCCP3nFWXo8mtdedz2A86H3rTSl",
    "image": "https://scontent-fra3-1.xx.fbcdn.net/v/t39.30808-6/724300063_122292328106023089_8179977212809567954_n.jpg?stp=dst-jpg_p720x720_tt6&_nc_cat=103&ccb=1-7&_nc_sid=e5c1b6&_nc_ohc=Y5jGWF-JrHUQ7kNvwFG2qXD&_nc_oc=AdojuyOWu0M9_3FZuE4UpMyYiec7anGfIAXUFihkj4JyYPTt_u93jAjlFnrUNkH_FcpGlTQsfhCUeJvqSRI_Ovkx&_nc_zt=23&_nc_ht=scontent-fra3-1.xx&_nc_gid=CxagG-mwOxYhpxRqpDf3kg&_nc_ss=7b289&oh=00_Af87B42ntMmmzcfmqAfN8Geqnjno87NRH9Wj4ezHYeSUlw&oe=6A3FA66E",
    "date": "Thu, 18 Jun 2026 06:30:07 GMT"
  },
  {
    "market": "MDS",
    "source": "mds",
    "title": "🛒✨ WEEKEND SPECIAL SALE ✨🛒 📍 MDS TATAU 📅 19 - 21 June 2026 Enjoy great deals and special member prices on selected i...",
    "link": "https://m.facebook.com/mdsmartofficial/posts/pfbid0UYf8hkwS3Gh31F1c9QkQa5Yw2mdWtUkw5HU9K7vXxN6Sqne3BspkxuwaJzoMDGP1l",
    "image": "https://scontent-fra3-2.xx.fbcdn.net/v/t39.30808-6/720487620_122292352436023089_703683425432028731_n.jpg?stp=dst-jpg_p526x296_tt6&_nc_cat=104&ccb=1-7&_nc_sid=e5c1b6&_nc_ohc=4JLictTQzbMQ7kNvwE8FDcz&_nc_oc=AdqXe7iSZAot6Dc29n_9I52mmlQZSLpjO_M9D9YSrClp17xv2xWw0DC957Feso7saNmNy5DZZdsg6X7vqhy-62yq&_nc_zt=23&_nc_ht=scontent-fra3-2.xx&_nc_gid=CxagG-mwOxYhpxRqpDf3kg&_nc_ss=7b289&oh=00_Af8esZzYXgRr2ZgjY_MDP8Uis0ET-tnafwNMNn4oieo7Qg&oe=6A3F8E29",
    "date": "Thu, 18 Jun 2026 04:00:15 GMT"
  }
]